mybible/__init__.py
mybible/core.py
mybible/utils.py
mybible-0.0.23.dist-info/LICENSE
mybible-0.0.23.dist-info/METADATA
mybible-0.0.23.dist-info/WHEEL
mybible-0.0.23.dist-info/top_level.txt
mybible-0.0.23.dist-info/RECORD
