Metadata-Version: 2.1
Name: mybible
Version: 0.0.23
Summary: API for MyBible modules
Home-page: https://github.com/PatriotRossii/MyBibleModuleParser
Author: Eoan Ermine
Author-email: patriotrossii2019@mail.ru
License: UNKNOWN
Project-URL: Bug Tracker, https://github.com/PatriotRossii/MyBibleModuleParser/issues
Platform: UNKNOWN
Classifier: Programming Language :: Python :: 3
Classifier: License :: OSI Approved :: MIT License
Classifier: Operating System :: OS Independent
Requires-Python: >=3.6
License-File: LICENSE
